mobility_datasets/__init__.py
mobility_datasets/cli/__init__.py
mobility_datasets/cli/main.py
mobility_datasets/common/__init__.py
mobility_datasets/common/base.py
mobility_datasets/kitti/__init__.py
mobility_datasets/kitti/converter.py
mobility_datasets/kitti/dataset.py
mobility_datasets/kitti/loader.py
mobility_datasets-0.1.2.dist-info/METADATA
mobility_datasets-0.1.2.dist-info/WHEEL
mobility_datasets-0.1.2.dist-info/entry_points.txt
mobility_datasets-0.1.2.dist-info/licenses/LICENSE
mobility_datasets-0.1.2.dist-info/RECORD
